[
  {
    "id": "cmex0gqcr0000s8kntyz5knba",
    "oldName": "Admin User",
    "email": "admin@dealmecca.pro",
    "newName": "VideoAOV5"
  },
  {
    "id": "cmek3qy340010s832ncu849nf",
    "oldName": "Alex Morgan",
    "email": "alex.morgan@72andsunny.com",
    "newName": "CAC2021"
  },
  {
    "id": "cmfcacwbt0012s8bfik8n4ajw",
    "oldName": "Anna Müller",
    "email": "anna@berlinStartup.de",
    "newName": "MediaCTV6"
  },
  {
    "id": "cmfcacxkm0016s8bfje3j9w10",
    "oldName": "Chloe Anderson",
    "email": "chloe@fashiontech.style",
    "newName": "DataDriven12"
  },
  {
    "id": "cmf7dntii0003s839iljzt7g5",
    "oldName": "Christian Juhl",
    "email": "christian.juhl@groupm.com",
    "newName": "CPC2024"
  },
  {
    "id": "cmeotk6ks0000s81dc27wa5mj",
    "oldName": "Christopher Wong",
    "email": "cswnyc@gmail.com",
    "newName": "u/Analytics95"
  },
  {
    "id": "cmfcactin000ts8bf60dnkxh3",
    "oldName": "Daniel Murphy",
    "email": "daniel@cryptotrading.io",
    "newName": "CampaignPrivacy8"
  },
  {
    "id": "cmejqwe1y0005s8qq58mtj9du",
    "oldName": "David Thompson",
    "email": "david.thompson@globalads.com",
    "newName": "CTVExpertOTT4"
  },
  {
    "id": "cmek3qxpm000ws832el6wucth",
    "oldName": "David Thompson",
    "email": "david.thompson@nike.com",
    "newName": "Privacy2021"
  },
  {
    "id": "cmfcacvq50010s8bf5feqim8n",
    "oldName": "Emma Clarke",
    "email": "emma@londontech.uk",
    "newName": "ExchangeFraud4"
  },
  {
    "id": "cmek3qxw3000ys832mibgo4nv",
    "oldName": "Emma Williams",
    "email": "emma.williams@ogilvy.com",
    "newName": "DCOTitan"
  },
  {
    "id": "cmfcacur6000xs8bferk19cav",
    "oldName": "Ethan Clark",
    "email": "ethan@cybersecurity.expert",
    "newName": "Retargeting49"
  },
  {
    "id": "cmfcacz63001bs8bfguf05ylj",
    "oldName": "Flynn O'Brien",
    "email": "flynn@maritimetech.sea",
    "newName": "LTV2022"
  },
  {
    "id": "cmfcacufx000ws8bfq39ijrw9",
    "oldName": "Grace Lee",
    "email": "grace@publicrelations.agency",
    "newName": "PrivacyStar"
  },
  {
    "id": "cmfcacsvo000rs8bfur751tjj",
    "oldName": "Hiroshi Tanaka",
    "email": "hiroshi@robotics.jp",
    "newName": "CAC2024"
  },
  {
    "id": "cmfcactth000us8bfc9psnk2k",
    "oldName": "Isabella Santos",
    "email": "isabella@socialimpact.org",
    "newName": "DSPMaster29"
  },
  {
    "id": "cmf7dntl30005s839cjolxhtc",
    "oldName": "James Wilson",
    "email": "james.wilson@disney.com",
    "newName": "u/CTVTitan"
  },
  {
    "id": "cmejqwdto0002s8qquhj1ldnm",
    "oldName": "Jennifer Kim",
    "email": "jennifer.kim@techstartup.com",
    "newName": "Campaign47"
  },
  {
    "id": "cmek3qxhx000us83299eqb3o0",
    "oldName": "Jennifer Kim",
    "email": "jennifer.kim@droga5.com",
    "newName": "PMPsGiant"
  },
  {
    "id": "cmfcacyj70019s8bfmrb408xu",
    "oldName": "Jordan Kim",
    "email": "jordan@musictech.sound",
    "newName": "Media97"
  },
  {
    "id": "cmfcacvde000zs8bfjbx1ndjf",
    "oldName": "Lucas Brown",
    "email": "lucas@supplychain.optimize",
    "newName": "CPMOracle"
  },
  {
    "id": "cmfcaczh9001cs8bf2dqvaicd",
    "oldName": "Luna Garcia",
    "email": "luna@spacetech.cosmos",
    "newName": "AttributionGuru"
  },
  {
    "id": "cmek3qxaz000ss832e7xphj9q",
    "oldName": "Marcus Rodriguez",
    "email": "marcus.rodriguez@bbdo.com",
    "newName": "OTTAce"
  },
  {
    "id": "cmfcacxw70017s8bf09jfr7uu",
    "oldName": "Mason Davis",
    "email": "mason@constructiontech.build",
    "newName": "u/DCOHero"
  },
  {
    "id": "cmfcacv2c000ys8bfj5n0mnhp",
    "oldName": "Mia Rodriguez",
    "email": "mia@eventplanning.co",
    "newName": "u/Omnichannel2"
  },
  {
    "id": "cmejqv8kc0001s8nmbksrldx5",
    "oldName": "Mike Rodriguez",
    "email": "mike.rodriguez@brandworks.com",
    "newName": "CPAHero"
  },
  {
    "id": "cmfcacs80000ps8bf0zyzb7w2",
    "oldName": "Mohammed Al-Rashid",
    "email": "mohammed@energyventures.sa",
    "newName": "CTVExpert41"
  },
  {
    "id": "cmfcacu4n000vs8bfkgdmli32",
    "oldName": "Noah Johnson",
    "email": "noah@gamestudio.dev",
    "newName": "CPCLegend"
  },
  {
    "id": "cmfcad03w001es8bfzdc1ia1g",
    "oldName": "Phoenix Lee",
    "email": "phoenix@quantumtech.future",
    "newName": "u/DTC2023"
  },
  {
    "id": "cmfcacw0u0011s8bf9opmyu3u",
    "oldName": "Pierre Dubois",
    "email": "pierre@parisventures.fr",
    "newName": "PrivacyMaster"
  },
  {
    "id": "cmfcacrwr000os8bfdr7lxkwd",
    "oldName": "Priya Patel",
    "email": "priya@edutech.startup",
    "newName": "Attribution47"
  },
  {
    "id": "cmekmhix00000s8o377oclaz7",
    "oldName": "Pro Admin User",
    "email": "pro@dealmecca.pro",
    "newName": "AOVHero"
  },
  {
    "id": "cmfcacwmr0013s8bfbfjahh2w",
    "oldName": "Raj Kumar",
    "email": "raj@mumbaifintech.in",
    "newName": "BrandSafetyDSP3"
  },
  {
    "id": "cmfcaczsy001ds8bfun9974n1",
    "oldName": "River Johnson",
    "email": "river@greentech.renewable",
    "newName": "Video33"
  },
  {
    "id": "cmfcacyui001as8bfnp6a0ryy",
    "oldName": "Ruby Singh",
    "email": "ruby@agritech.farm",
    "newName": "AdTechGuru78"
  },
  {
    "id": "cmfcad0f6001fs8bf0l8x3avr",
    "oldName": "Sage Miller",
    "email": "sage@wellness.mindful",
    "newName": "u/DataDriven34"
  },
  {
    "id": "cmfcacwxz0014s8bfrh3pwrdz",
    "oldName": "Samantha Wilson",
    "email": "sam@sustainabletech.eco",
    "newName": "Campaign75"
  },
  {
    "id": "cmek3qx2g000qs8323pqjucnf",
    "oldName": "Sarah Chen",
    "email": "sarah.chen@wk.com",
    "newName": "PMPsPrime"
  },
  {
    "id": "cmejqubg80002s8j0jjcbxug0",
    "oldName": "Sarah Chen",
    "email": "sarah.chen@creativehq.com",
    "newName": "MediaBuyerRTB8"
  },
  {
    "id": "cmf7dnte70001s83923oo13ez",
    "oldName": "Sarah Chen",
    "email": "sarah.chen@publicis.com",
    "newName": "CDPChief"
  },
  {
    "id": "cmfcacskk000qs8bfr0wdyhw1",
    "oldName": "Sophie Dubois",
    "email": "sophie@luxurybrand.fr",
    "newName": "DataDrivenRTB1"
  },
  {
    "id": "cmejqbuck0000s8opienjp5l8",
    "oldName": "Test User",
    "email": "test@example.com",
    "newName": "u/Identity34"
  },
  {
    "id": "cmfcacx9e0015s8bf3zffvdjj",
    "oldName": "Tyler Martinez",
    "email": "tyler@sportsbusiness.pro",
    "newName": "ExchangeCTV1"
  },
  {
    "id": "cmfcact6n000ss8bf329lfx5x",
    "oldName": "Victoria Adams",
    "email": "victoria@foodtech.startup",
    "newName": "ViewabilityProAOV4"
  },
  {
    "id": "cmfcacy850018s8bf2qhozg3r",
    "oldName": "Zoe Thompson",
    "email": "zoe@traveltech.explore",
    "newName": "Header6"
  },
  {
    "id": "cmfcacmbf0006s8bf566ngi0c",
    "oldName": "angellisa",
    "email": "lisa@angelgroup.net",
    "newName": "BrandSafety3"
  },
  {
    "id": "cmfcacqo2000ks8bfiggi05um",
    "oldName": "biotechdoc",
    "email": "p.wilson@biotech.research",
    "newName": "Journey38"
  },
  {
    "id": "cmfcacqcy000js8bfsx5dj2gl",
    "oldName": "codeconsultant",
    "email": "ryan@devConsultant.tech",
    "newName": "CDPPrime"
  },
  {
    "id": "cmfcaco5i000cs8bfi79uajab",
    "oldName": "commercialjen",
    "email": "jennifer@commercialre.com",
    "newName": "CDP2023"
  },
  {
    "id": "cmfcacl2b0002s8bfbs4nx47l",
    "oldName": "consultingpro",
    "email": "j.martinez@consulting.pro",
    "newName": "Journey99"
  },
  {
    "id": "cmfcacq1u000is8bfe8fwv8ht",
    "oldName": "contentqueen",
    "email": "nicole@contentcreator.co",
    "newName": "Audience73"
  },
  {
    "id": "cmfcacpqy000hs8bf9zet74cs",
    "oldName": "designalex",
    "email": "alex.taylor@freelance.design",
    "newName": "Analytics27"
  },
  {
    "id": "cmfcackp00001s8bfwm32exi5",
    "oldName": "ecomexpert",
    "email": "mike.chen@ecommerce.biz",
    "newName": "u/DataDriven45"
  },
  {
    "id": "cmfcacle40003s8bfc6zqlftn",
    "oldName": "fintechdave",
    "email": "david@fintech.startup",
    "newName": "PrivacyGuru"
  },
  {
    "id": "cmfcaclpf0004s8bfte6dzqcn",
    "oldName": "healthinnovator",
    "email": "emma.t@healthtech.co",
    "newName": "ROASKing"
  },
  {
    "id": "cmfcacpfu000gs8bfbln31qen",
    "oldName": "hrkelly",
    "email": "kelly@hrConsulting.biz",
    "newName": "Native17"
  },
  {
    "id": "cmfcacot4000es8bf7qjzx1s6",
    "oldName": "legaleagle",
    "email": "maria@legalservices.law",
    "newName": "u/KeywordCPM6"
  },
  {
    "id": "cmfcacrlo000ns8bfb1h2o2l0",
    "oldName": "logisticsbrian",
    "email": "brian@logistics.express",
    "newName": "RTBWizard"
  },
  {
    "id": "cmfcacqza000ls8bf81g0ofk0",
    "oldName": "manufacturingcarlos",
    "email": "carlos@manufacturing.co",
    "newName": "u/Quality32"
  },
  {
    "id": "cmfcacn800009s8bflory7gn4",
    "oldName": "marketingguru",
    "email": "chris.w@digitalmarketing.co",
    "newName": "Waterfall77"
  },
  {
    "id": "cmfcacp4m000fs8bf5tpa4biy",
    "oldName": "numberscruncher",
    "email": "tom.b@accounting.firm",
    "newName": "DataDrivenCPA2"
  },
  {
    "id": "cmfcacmm70007s8bfrybuj3pp",
    "oldName": "pejames",
    "email": "james.r@peequity.fund",
    "newName": "PrivacyElite"
  },
  {
    "id": "cmfcacnuf000bs8bfh0g3deb4",
    "oldName": "propertydealer",
    "email": "mark.j@realestate.pro",
    "newName": "CPMHero"
  },
  {
    "id": "cmfcacra9000ms8bfo3fk3n6d",
    "oldName": "retailash",
    "email": "ashley@retailchain.com",
    "newName": "CACLeader"
  },
  {
    "id": "cmfcacmx30008s8bfcjiafhd0",
    "oldName": "salesace",
    "email": "a.davis@salesforce.expert",
    "newName": "PII2023"
  },
  {
    "id": "cmfcacm0n0005s8bfgdccxn7j",
    "oldName": "siliconinvestor",
    "email": "r.williams@vcfund.com",
    "newName": "CPMExpert"
  },
  {
    "id": "cmfcacnj4000as8bf64az4wij",
    "oldName": "socialmediarace",
    "email": "rachel@socialmedia.agency",
    "newName": "DCO2022"
  },
  {
    "id": "cmfcack7g0000s8bf9jqpkfwc",
    "oldName": "techfounder2024",
    "email": "sarah.j@techstartup.co",
    "newName": "ViewabilityProLTV1"
  },
  {
    "id": "cmfcacogt000ds8bft0rxq7il",
    "oldName": "webdesignsteve",
    "email": "steve@webdesign.studio",
    "newName": "Exchange89"
  }
]